Metadata-Version: 2.1
Name: odoo8-addon-document-page
Version: 8.0.1.0.2.99.dev31
Summary: Document Page
Home-page: http://www.openerp.com/
Author: OpenERP SA,Odoo Community Association (OCA)
Author-email: support@odoo-community.org
License: AGPL-3
Platform: UNKNOWN
Classifier: Programming Language :: Python
Classifier: Framework :: Odoo
Classifier: License :: OSI Approved :: GNU Affero General Public License v3
Requires-Python: ~=2.7
Requires-Dist: odoo (<9.0a,>=8.0a)
